buckets_hunter/__init__.py
buckets_hunter/__main__.py
buckets_hunter/conf/__init__.py
buckets_hunter/conf/scan_config.py
buckets_hunter/data/__init__.py
buckets_hunter/data/buckets_wordlist.txt
buckets_hunter/modules/__init__.py
buckets_hunter/modules/aws/__init__.py
buckets_hunter/modules/aws/aws_scanner.py
buckets_hunter/modules/azure/__init__.py
buckets_hunter/modules/azure/azure_scanner.py
buckets_hunter/modules/azure/regions.py
buckets_hunter/modules/gcp/__init__.py
buckets_hunter/modules/gcp/gcp_scanner.py
buckets_hunter/utils/__init__.py
buckets_hunter/utils/dns.py
buckets_hunter/utils/hunter_utils.py
buckets_hunter/utils/notify.py
bucketshunter-2.0.dist-info/LICENSE
bucketshunter-2.0.dist-info/METADATA
bucketshunter-2.0.dist-info/WHEEL
bucketshunter-2.0.dist-info/entry_points.txt
bucketshunter-2.0.dist-info/top_level.txt
bucketshunter-2.0.dist-info/RECORD
