Metadata-Version: 2.1
Name: bucketshunter
Version: 2.0
Summary: Scan for open buckets, misconfigurations and dump contents.
Home-page: https://github.com/danielazulayy/BucketsHunter
Author: Daniel Azulay
Author-email: serializator@gmail.com
Project-URL: Bug Tracker, https://github.com/danielazulayy/BucketsHunter
Classifier: Programming Language :: Python :: 3.6
Classifier: Programming Language :: Python :: 3.7
Classifier: Programming Language :: Python :: 3.8
Classifier: Programming Language :: Python :: 3.9
Classifier: Topic :: Security
Classifier: License :: OSI Approved :: MIT License
Classifier: Operating System :: OS Independent
Requires-Python: >=3.6
License-File: LICENSE
Requires-Dist: boto3
Requires-Dist: botocore
Requires-Dist: certifi
Requires-Dist: charset-normalizer
Requires-Dist: dnspython
Requires-Dist: idna
Requires-Dist: jmespath
Requires-Dist: loguru
Requires-Dist: python-dateutil
Requires-Dist: requests
Requires-Dist: s3transfer
Requires-Dist: six
Requires-Dist: ujson
Requires-Dist: urllib3
